{
    "annotations": {
      "list": [
        {
          "builtIn": 1,
          "datasource": {
            "type": "grafana",
            "uid": "-- Grafana --"
          },
          "enable": true,
          "hide": true,
          "iconColor": "rgba(0, 211, 255, 1)",
          "name": "Annotations & Alerts",
          "type": "dashboard"
        }
      ]
    },
    "editable": true,
    "fiscalYearStartMonth": 0,
    "graphTooltip": 0,
    "id": 2,
    "links": [],
    "panels": [
      {
        "datasource": {
          "type": "prometheus",
          "uid": "prometheus"
        },
        "description": "Time spent on receiving the response from the upstream server on last API call",
        "fieldConfig": {
          "defaults": {
            "color": {
              "mode": "palette-classic"
            },
            "custom": {
              "axisBorderShow": false,
              "axisCenteredZero": false,
              "axisColorMode": "text",
              "axisLabel": "",
              "axisPlacement": "auto",
              "barAlignment": 0,
              "barWidthFactor": 0.6,
              "drawStyle": "line",
              "fillOpacity": 0,
              "gradientMode": "none",
              "hideFrom": {
                "legend": false,
                "tooltip": false,
                "viz": false
              },
              "insertNulls": 600000,
              "lineInterpolation": "linear",
              "lineWidth": 1,
              "pointSize": 5,
              "scaleDistribution": {
                "log": 2,
                "type": "log"
              },
              "showPoints": "auto",
              "spanNulls": false,
              "stacking": {
                "group": "A",
                "mode": "none"
              },
              "thresholdsStyle": {
                "mode": "off"
              }
            },
            "mappings": [],
            "thresholds": {
              "mode": "absolute",
              "steps": [
                {
                  "color": "green",
                  "value": null
                },
                {
                  "color": "red",
                  "value": 80
                }
              ]
            }
          },
          "overrides": []
        },
        "gridPos": {
          "h": 8,
          "w": 24,
          "x": 0,
          "y": 0
        },
        "id": 1,
        "options": {
          "legend": {
            "calcs": [],
            "displayMode": "list",
            "placement": "right",
            "showLegend": true
          },
          "tooltip": {
            "mode": "single",
            "sort": "none"
          }
        },
        "pluginVersion": "11.3.0",
        "targets": [
          {
            "datasource": {
              "type": "prometheus",
              "uid": "prometheus"
            },
            "editorMode": "code",
            "expr": "avg(upstream_response_time{request=~\"GET /dashboard.*\"})",
            "hide": false,
            "instant": false,
            "legendFormat": "/dashboard/*",
            "range": true,
            "refId": "A"
          },
          {
            "datasource": {
              "type": "prometheus",
              "uid": "prometheus"
            },
            "editorMode": "code",
            "expr": "avg(upstream_response_time{request=~\"GET /gold-price/.*\"})",
            "hide": false,
            "instant": false,
            "legendFormat": "/gold-price/*",
            "range": true,
            "refId": "B"
          },
          {
            "datasource": {
              "type": "prometheus",
              "uid": "prometheus"
            },
            "disableTextWrap": false,
            "editorMode": "code",
            "expr": "avg(upstream_response_time{request=~\"GET /rate-exchange/.*\"})",
            "fullMetaSearch": false,
            "hide": false,
            "includeNullMetadata": true,
            "instant": false,
            "legendFormat": "/rate-exchange/*",
            "range": true,
            "refId": "C",
            "useBackend": false
          }
        ],
        "title": "Service Response Time",
        "type": "timeseries"
      },
      {
        "collapsed": false,
        "gridPos": {
          "h": 1,
          "w": 24,
          "x": 0,
          "y": 8
        },
        "id": 3,
        "panels": [],
        "title": "Endpoint Detail",
        "type": "row"
      },
      {
        "datasource": {
          "type": "prometheus",
          "uid": "prometheus"
        },
        "fieldConfig": {
          "defaults": {
            "color": {
              "mode": "palette-classic"
            },
            "custom": {
              "axisBorderShow": false,
              "axisCenteredZero": false,
              "axisColorMode": "text",
              "axisLabel": "",
              "axisPlacement": "auto",
              "barAlignment": 0,
              "barWidthFactor": 0.6,
              "drawStyle": "line",
              "fillOpacity": 0,
              "gradientMode": "none",
              "hideFrom": {
                "legend": false,
                "tooltip": false,
                "viz": false
              },
              "insertNulls": false,
              "lineInterpolation": "linear",
              "lineWidth": 1,
              "pointSize": 5,
              "scaleDistribution": {
                "type": "linear"
              },
              "showPoints": "auto",
              "spanNulls": false,
              "stacking": {
                "group": "A",
                "mode": "none"
              },
              "thresholdsStyle": {
                "mode": "off"
              }
            },
            "mappings": [],
            "thresholds": {
              "mode": "absolute",
              "steps": [
                {
                  "color": "green",
                  "value": null
                },
                {
                  "color": "red",
                  "value": 80
                }
              ]
            }
          },
          "overrides": []
        },
        "gridPos": {
          "h": 8,
          "w": 8,
          "x": 0,
          "y": 9
        },
        "id": 2,
        "options": {
          "legend": {
            "calcs": [],
            "displayMode": "list",
            "placement": "bottom",
            "showLegend": true
          },
          "tooltip": {
            "mode": "single",
            "sort": "none"
          }
        },
        "pluginVersion": "11.3.0",
        "targets": [
          {
            "datasource": {
              "type": "prometheus",
              "uid": "prometheus"
            },
            "editorMode": "code",
            "expr": "upstream_response_time{request=~\"GET /dashboard[^?]*\"}",
            "instant": false,
            "legendFormat": "{{request}}",
            "range": true,
            "refId": "A"
          }
        ],
        "title": "Dashboard",
        "type": "timeseries"
      },
      {
        "datasource": {
          "type": "prometheus",
          "uid": "prometheus"
        },
        "fieldConfig": {
          "defaults": {
            "color": {
              "mode": "palette-classic"
            },
            "custom": {
              "axisBorderShow": false,
              "axisCenteredZero": false,
              "axisColorMode": "text",
              "axisLabel": "",
              "axisPlacement": "auto",
              "barAlignment": 0,
              "barWidthFactor": 0.6,
              "drawStyle": "line",
              "fillOpacity": 0,
              "gradientMode": "none",
              "hideFrom": {
                "legend": false,
                "tooltip": false,
                "viz": false
              },
              "insertNulls": false,
              "lineInterpolation": "linear",
              "lineWidth": 1,
              "pointSize": 5,
              "scaleDistribution": {
                "type": "linear"
              },
              "showPoints": "auto",
              "spanNulls": false,
              "stacking": {
                "group": "A",
                "mode": "none"
              },
              "thresholdsStyle": {
                "mode": "off"
              }
            },
            "mappings": [],
            "thresholds": {
              "mode": "absolute",
              "steps": [
                {
                  "color": "green",
                  "value": null
                },
                {
                  "color": "red",
                  "value": 80
                }
              ]
            }
          },
          "overrides": []
        },
        "gridPos": {
          "h": 8,
          "w": 8,
          "x": 8,
          "y": 9
        },
        "id": 4,
        "options": {
          "legend": {
            "calcs": [],
            "displayMode": "list",
            "placement": "bottom",
            "showLegend": true
          },
          "tooltip": {
            "mode": "single",
            "sort": "none"
          }
        },
        "pluginVersion": "11.3.0",
        "targets": [
          {
            "datasource": {
              "type": "prometheus",
              "uid": "prometheus"
            },
            "editorMode": "code",
            "expr": "upstream_response_time{request=~\"GET /gold-price[^?]*\"}",
            "instant": false,
            "legendFormat": "{{request}}",
            "range": true,
            "refId": "A"
          }
        ],
        "title": "Gold price",
        "type": "timeseries"
      },
      {
        "datasource": {
          "type": "prometheus",
          "uid": "prometheus"
        },
        "fieldConfig": {
          "defaults": {
            "color": {
              "mode": "palette-classic"
            },
            "custom": {
              "axisBorderShow": false,
              "axisCenteredZero": false,
              "axisColorMode": "text",
              "axisLabel": "",
              "axisPlacement": "auto",
              "barAlignment": 0,
              "barWidthFactor": 0.6,
              "drawStyle": "line",
              "fillOpacity": 0,
              "gradientMode": "none",
              "hideFrom": {
                "legend": false,
                "tooltip": false,
                "viz": false
              },
              "insertNulls": false,
              "lineInterpolation": "linear",
              "lineWidth": 1,
              "pointSize": 5,
              "scaleDistribution": {
                "type": "linear"
              },
              "showPoints": "auto",
              "spanNulls": false,
              "stacking": {
                "group": "A",
                "mode": "none"
              },
              "thresholdsStyle": {
                "mode": "off"
              }
            },
            "mappings": [],
            "thresholds": {
              "mode": "absolute",
              "steps": [
                {
                  "color": "green",
                  "value": null
                },
                {
                  "color": "red",
                  "value": 80
                }
              ]
            }
          },
          "overrides": []
        },
        "gridPos": {
          "h": 8,
          "w": 8,
          "x": 16,
          "y": 9
        },
        "id": 5,
        "options": {
          "legend": {
            "calcs": [],
            "displayMode": "list",
            "placement": "bottom",
            "showLegend": true
          },
          "tooltip": {
            "mode": "single",
            "sort": "none"
          }
        },
        "pluginVersion": "11.3.0",
        "targets": [
          {
            "datasource": {
              "type": "prometheus",
              "uid": "prometheus"
            },
            "editorMode": "code",
            "expr": "upstream_response_time{request=~\"GET /rate-exchange[^?]*\"}",
            "instant": false,
            "legendFormat": "{{request}}",
            "range": true,
            "refId": "A"
          }
        ],
        "title": "Exchange rate",
        "type": "timeseries"
      }
    ],
    "preload": false,
    "refresh": "5s",
    "schemaVersion": 40,
    "tags": [],
    "templating": {
      "list": []
    },
    "time": {
      "from": "now-5m",
      "to": "now"
    },
    "timepicker": {},
    "timezone": "browser",
    "title": "API Response Time",
    "uid": "LatencyDas",
    "version": 22,
    "weekStart": ""
  }
